MANIFEST.in
README
_version.py
setup.cfg
setup.py
docu/__init__.py
docu/backend_base.py
docu/dist.py
docu/document_base.py
docu/fields.py
docu/validators.py
docu.egg-info/PKG-INFO
docu.egg-info/SOURCES.txt
docu.egg-info/dependency_links.txt
docu.egg-info/entry_points.txt
docu.egg-info/requires.txt
docu.egg-info/top_level.txt
docu/ext/__init__.py
docu/ext/forms.py
docu/ext/mongodb/__init__.py
docu/ext/mongodb/converters.py
docu/ext/mongodb/lookups.py
docu/ext/shelve_db/__init__.py
docu/ext/shelve_db/converters.py
docu/ext/shelve_db/lookups.py
docu/ext/shove_db/__init__.py
docu/ext/tokyo_cabinet/__init__.py
docu/ext/tokyo_cabinet/converters.py
docu/ext/tokyo_cabinet/lookups.py
docu/ext/tokyo_tyrant/__init__.py
docu/ext/tokyo_tyrant/converters.py
docu/ext/tokyo_tyrant/lookups.py
docu/ext/tokyo_tyrant/managers.py
docu/ext/tokyo_tyrant/query.py
docu/ext/tokyo_tyrant/storage.py
docu/utils/__init__.py
docu/utils/data_structures.py